{"task": 2, "model_type": "TransformerLSTMPlus", "data_params": {"interval_length": 800, "stride_train": 200, "stride_eval": 300, "fps": 50, "columns_to_remove": "openpose, c_openface", "label_creation": "stride_eval", "nan_handling": "zeros", "oversampling_rate": 0.2, "undersampling_rate": 0.0, "rescaling": "standardization", "start_padding": true}, "model_params": {"d_model": 160, "nhead": 8, "proj_dropout": 0.2, "num_encoder_layers": 1536, "dim_feedforward": 2560, "dropout": 0.4, "num_rnn_layers": 2, "bs": 16, "lr": 0.00012537303710545165, "loss": "FocalLossFlat"}, "stats": {"accuracy": 0.7986360134317594, "macro f1": 0.7022042482782989}}